Metadata-Version: 1.1
Name: khrplot
Version: 0.0.3
Summary: import google sheets and plot any columns you choose
Home-page: UNKNOWN
Author: Hemanth Reddy
Author-email: hemanthreddy.kolli@gmail.com
License: MIT
Keywords: plots
Platform: UNKNOWN
Classifier: Development Status :: 5 - Production/Stable
Classifier: Intended Audience :: Education
Classifier: Operating System :: Microsoft :: Windows :: Windows 10
Classifier: License :: OSI Approved :: MIT License
Classifier: Programming Language :: Python :: 3
